README
setup.py
skcv/__init__.py
skcv/_build.py
skcv/setup.py
skcv/version.py
skcv/graph/__init__.py
skcv/graph/rag.py
skcv/graph/setup.py
skcv/graph/tests/__init__.py
skcv/graph/tests/test_rag.py
skcv/image/__init__.py
skcv/image/setup.py
skcv/image/features/__init__.py
skcv/image/features/setup.py
skcv/image/filter/__init__.py
skcv/image/filter/setup.py
skcv/image/segmentation/__init__.py
skcv/image/segmentation/hierarchical.py
skcv/image/segmentation/region_descriptors.py
skcv/image/segmentation/region_distances.py
skcv/image/segmentation/setup.py
skcv/multiview/__init__.py
skcv/multiview/setup.py
skcv/multiview/autocalibration/__init__.py
skcv/multiview/autocalibration/setup.py
skcv/multiview/n_views/__init__.py
skcv/multiview/n_views/setup.py
skcv/multiview/two_views/__init__.py
skcv/multiview/two_views/setup.py
skcv/util/__init__.py
skcv/util/false_color.py
skcv/util/setup.py
skcv/video/__init__.py
skcv/video/setup.py
skcv/video/optical_flow/__init__.py
skcv/video/optical_flow/io.py
skcv/video/optical_flow/reliability.py
skcv/video/optical_flow/setup.py
skcv/video/optical_flow/visualization.py
skcv/video/segmentation/__init__.py
skcv/video/segmentation/frame_slic.py
skcv/video/segmentation/setup.py
skicit_cv.egg-info/PKG-INFO
skicit_cv.egg-info/SOURCES.txt
skicit_cv.egg-info/dependency_links.txt
skicit_cv.egg-info/not-zip-safe
skicit_cv.egg-info/top_level.txt