Metadata-Version: 1.1
Name: skicit-cv
Version: 0.1dev
Summary: Computer Vision library for Python
Home-page: http://github.com/guillempalou/scikit-cv
Author: Guillem Palou
Author-email: guillem.palou@gmail.com
License: MIT
Download-URL: http://github.com/guillempalou/scikit-cv
Platform: UNKNOWN
Classifier: Development Status :: 4 - Beta
Classifier: Environment :: Console
Classifier: Intended Audience :: Developers
Classifier: Intended Audience :: Science/Research
Classifier: License :: OSI Approved :: MIT License
Classifier: Programming Language :: C++
Classifier: Programming Language :: Python
Classifier: Programming Language :: Python :: 3
Classifier: Topic :: Scientific/Engineering
Classifier: Operating System :: Microsoft :: Windows
Classifier: Operating System :: POSIX
Classifier: Operating System :: Unix
Classifier: Operating System :: MacOS
